opendsm/__init__.py
opendsm/__version__.py
opendsm/common/__init__.py
opendsm/common/abstract_data_processor.py
opendsm/common/abstract_data_settings.py
opendsm/common/adaptive_loss.py
opendsm/common/adaptive_loss_Z.py
opendsm/common/base_settings.py
opendsm/common/const.py
opendsm/common/hourly_interpolation.py
opendsm/common/metrics.py
opendsm/common/pydantic_utils.py
opendsm/common/test_data.py
opendsm/common/utils.py
opendsm/common/clustering/__init__.py
opendsm/common/clustering/bisect_k_means.py
opendsm/common/clustering/cluster.py
opendsm/common/clustering/scoring.py
opendsm/common/clustering/settings.py
opendsm/common/clustering/transform.py
opendsm/drmeter/__init__.py
opendsm/drmeter/models/__init__.py
opendsm/drmeter/models/caltrack/__init__.py
opendsm/drmeter/models/caltrack/data.py
opendsm/drmeter/models/caltrack/model.py
opendsm/eemeter/__init__.py
opendsm/eemeter/common/__init__.py
opendsm/eemeter/common/data_processor_utilities.py
opendsm/eemeter/common/data_settings.py
opendsm/eemeter/common/exceptions.py
opendsm/eemeter/common/features.py
opendsm/eemeter/common/sufficiency_criteria.py
opendsm/eemeter/common/transform.py
opendsm/eemeter/common/warnings.py
opendsm/eemeter/models/__init__.py
opendsm/eemeter/models/billing/__init__.py
opendsm/eemeter/models/billing/data.py
opendsm/eemeter/models/billing/model.py
opendsm/eemeter/models/billing/plot.py
opendsm/eemeter/models/billing/settings.py
opendsm/eemeter/models/billing/weighted_model.py
opendsm/eemeter/models/daily/__init__.py
opendsm/eemeter/models/daily/data.py
opendsm/eemeter/models/daily/fit_base_models.py
opendsm/eemeter/models/daily/model.py
opendsm/eemeter/models/daily/objective_function.py
opendsm/eemeter/models/daily/optimize.py
opendsm/eemeter/models/daily/optimize_results.py
opendsm/eemeter/models/daily/parameters.py
opendsm/eemeter/models/daily/plot.py
opendsm/eemeter/models/daily/base_models/__init__.py
opendsm/eemeter/models/daily/base_models/c_hdd_tidd.py
opendsm-1.2.6.dist-info/licenses/LICENSE
opendsm-1.2.6.dist-info/METADATA
opendsm-1.2.6.dist-info/WHEEL
opendsm-1.2.6.dist-info/top_level.txt
opendsm-1.2.6.dist-info/RECORD
