Metadata-Version: 2.4
Name: opendsm
Version: 1.2.6
Summary: Measure demand-side program impacts
Home-page: http://github.com/opendsm/opendsm
Author: opendsm
Author-email: opendsm@lists.lfenergy.org
License: Apache 2.0
Classifier: License :: OSI Approved :: Apache Software License
Classifier: Programming Language :: Python
Classifier: Programming Language :: Python :: 3
Classifier: Programming Language :: Python :: 3.9
Classifier: Programming Language :: Python :: 3.10
Classifier: Programming Language :: Python :: 3.11
Classifier: Programming Language :: Python :: 3.12
License-File: LICENSE
Requires-Dist: attrs
Requires-Dist: click
Requires-Dist: fdasrsf>=2.4.1
Requires-Dist: nlopt
Requires-Dist: numba
Requires-Dist: numpy>=1.24.4
Requires-Dist: pandas>=1.1.0
Requires-Dist: pyarrow
Requires-Dist: pydantic>=2.0
Requires-Dist: pywavelets
Requires-Dist: requests
Requires-Dist: scikit-fda
Requires-Dist: scikit-learn>=1.3.0
Requires-Dist: scipy>=1.10.1
Requires-Dist: statsmodels
Dynamic: author
Dynamic: author-email
Dynamic: classifier
Dynamic: description
Dynamic: description-content-type
Dynamic: home-page
Dynamic: license
Dynamic: license-file
Dynamic: requires-dist
Dynamic: summary
